[
  {
    "id": 1,
    "title": {
      "en": "The Five Pillars of Islam",
      "bn": "ইসলামের পাঁচটি স্তম্ভ",
      "ar": "أركان الإسلام الخمسة"
    },
    "body": {
      "en": "\n                    <h4>1. Shahada (Declaration of Faith)</h4>\n                    <p>The Shahada is the fundamental belief and the core of Islam. It is the first step to becoming a Muslim.</p>\n                    <div class=\"tutorial-arabic\">أَشْهَدُ أَنْ لَا إِلٰهَ إِلَّا اللّٰهُ وَأَشْهَدُ أَنَّ مُحَمَّدًا رَسُولُ اللّٰهِ</div>\n                    <div class=\"tutorial-pronunciation\">🔊 Ash-hadu an la ilaha illallah, wa ash-hadu anna Muhammadan Rasulullah</div>\n                    <p>\"I bear witness that there is no god but Allah, and I bear witness that Muhammad is the Messenger of Allah.\"</p>\n                    \n                    <h4>2. Salah (Prayer)</h4>\n                    <p>Salah is the direct link between the worshipper and Allah. Muslims must perform five obligatory prayers daily facing the Kaaba in Mecca: Fajr (dawn), Dhuhr (midday), Asr (late afternoon), Maghrib (sunset), and Isha (night). Salah purifies the heart and prevents evil deeds.</p>\n                    \n                    <h4>3. Zakat (Almsgiving)</h4>\n                    <p>Zakat is a mandatory charitable contribution given to those in need. It purifies wealth and maintains economic balance in society. It is calculated as 2.5% of one's accumulated wealth that has reached the minimum threshold (Nisab) over a lunar year.</p>\n                    \n                    <h4>4. Sawm (Fasting)</h4>\n                    <p>Fasting is obligatory during the 9th Islamic month of Ramadan. Muslims abstain from food, drink, and worldly desires from dawn (Fajr) to sunset (Maghrib). It builds self-control (Taqwa), gratitude to Allah, and shared empathy for the hungry.</p>\n                    \n                    <h4>5. Hajj (Pilgrimage)</h4>\n                    <p>Hajj is the annual pilgrimage to the Kaaba in Mecca, Saudi Arabia. It must be performed in the month of Dhu al-Hijjah. It is a mandatory duty for all Muslims who are physically and financially able to undertake the journey at least once in their lifetime, symbolizing complete unity and equality.</p>\n                ",
      "bn": "\n                    <h4>1. শাহাদা (বিশ্বাসের ঘোষণা)</h4>\n                    <p>শাহাদা হল ইসলামের মৌলিক বিশ্বাস ও মূল। এটা মুসলমান হওয়ার প্রথম ধাপ।</p>\n                    <div class=\"tutorial-arabic\">أَشْهَدُ أَنْ لَا إِلٰهَ إِلَّا اللّٰهُ وَأَشْهَدُ أَنَّ مُحَمَّدًا رَسُولُ اللّٰهِ</div>\n                    <div class=\"tutorial-pronunciation\">🔊 Ash-hadu an la ilaha illallah, wa ash-hadu anna Muhammadan Rasulullah</div>\n                    <p>\"আমি সাক্ষ্য দিচ্ছি যে আল্লাহ ব্যতীত কোন উপাস্য নেই এবং আমি সাক্ষ্য দিচ্ছি যে মুহাম্মদ আল্লাহর রাসূল।\"</p>\n                    \n                    <h4>2. সালাহ (নামাজ)</h4>\n                    <p>সালাত হল ইবাদতকারী ও আল্লাহর মধ্যে সরাসরি যোগসূত্র। মুসলমানদের অবশ্যই মক্কায় কাবার দিকে মুখ করে প্রতিদিন পাঁচটি ফরজ নামাজ আদায় করতে হবে: ফজর (ভোর), ধুহর (দুপুর), আসর (বিকালের শেষ দিকে), মাগরিব (সূর্যাস্ত) এবং ইশা (রাত্রি)। সালাত অন্তরকে পরিশুদ্ধ করে এবং খারাপ কাজ থেকে বিরত রাখে।</p>\n                    \n                    <h4>3. যাকাত (দান)</h4>\n                    <p>জাকাত হল একটি বাধ্যতামূলক দাতব্য দান যা অভাবীদের জন্য প্রদত্ত। এটি সম্পদকে পরিশুদ্ধ করে এবং সমাজে অর্থনৈতিক ভারসাম্য রক্ষা করে। এটাকে একজনের সঞ্চিত সম্পদের 2.5% হিসাবে গণনা করা হয় যা একটি চান্দ্র বছরে সর্বনিম্ন থ্রেশহোল্ডে (নিসাব) পৌঁছেছে।</p>\n                    \n                    <h4>4. সাওম (রোজা)</h4>\n                    <p>নবম ইসলামি মাসে রমজান মাসে রোজা রাখা ফরজ। মুসলমানরা ভোর (ফজর) থেকে সূর্যাস্ত (মাগরিব) পর্যন্ত খাদ্য, পানীয় এবং পার্থিব কামনা-বাসনা থেকে বিরত থাকে। এটি আত্ম-নিয়ন্ত্রণ (তাকওয়া), আল্লাহর প্রতি কৃতজ্ঞতা এবং ক্ষুধার্তদের জন্য সহানুভূতি তৈরি করে।</p>\n                    \n                    <h4>5. হজ (তীর্থযাত্রা)</h4>\n                    <p>হজ হল সৌদি আরবের মক্কায় কাবার বার্ষিক তীর্থযাত্রা। এটি অবশ্যই জুল-হিজ্জাহ মাসে করা উচিত। এটি সমস্ত মুসলমানদের জন্য একটি বাধ্যতামূলক কর্তব্য যারা শারীরিক এবং আর্থিকভাবে সক্ষম তাদের জীবনে অন্তত একবার ভ্রমণ করতে পারে, যা সম্পূর্ণ ঐক্য ও সাম্যের প্রতীক।</p>\n                ",
      "ar": "\n                    <h4>1. الشهادة (إعلان الإيمان)</h4>\n                    <p>الشهادة هي العقيدة الأساسية وجوهر الإسلام. إنها الخطوة الأولى لتصبح مسلماً.</p>\n                    <div class=\"tutorial-arabic\">أَشْهَدُ أَنْ لَا إِلٰهَ إِلَّا اللّٰهُ وَأَشْهَدُ أَنَّ مُحَمَّدًا رَسُولُ اللّٰهِ</div>\n                    <div class=\"tutorial-pronunciation\">🔊 Ash-hadu an la ilaha illallah, wa ash-hadu anna Muhammadan Rasulullah</div>\n                    <p>\"أشهد أن لا إله إلا الله، وأشهد أن محمداً رسول الله\".</p>\n                    \n                    <h4>2. صلاح (الصلاة)</h4>\n                    <p>الصلاة هي الصلة المباشرة بين العبد والله. يجب على المسلمين أداء خمس صلوات مفروضة يوميًا في مواجهة الكعبة في مكة: الفجر (الفجر)، الظهر (منتصف النهار)، العصر (في وقت متأخر بعد الظهر)، المغرب (غروب الشمس)، والعشاء (ليلاً). الصلاة تطهر القلب وتنهى عن المنكرات.</p>\n                    \n                    <h4>3. الزكاة</h4>\n                    <p>الزكاة هي مساهمة خيرية إلزامية تعطى للمحتاجين. ينقي الثروة ويحافظ على التوازن الاقتصادي في المجتمع. ويتم حسابه على أنه 2.5% من الثروة المتراكمة التي وصلت إلى الحد الأدنى (النصاب) خلال سنة قمرية.</p>\n                    \n                    <h4>4. الصوم</h4>\n                    <p>الصيام واجب خلال الشهر الإسلامي التاسع من رمضان. يمتنع المسلمون عن الطعام والشراب والرغبات الدنيوية من الفجر (الفجر) إلى غروب الشمس (المغرب). فهو يبني ضبط النفس (التقوى)، والشكر لله، والتعاطف المشترك مع الجياع.</p>\n                    \n                    <h4>5. الحج (الحج)</h4>\n                    <p>الحج هو الحج السنوي إلى الكعبة المشرفة في مكة بالمملكة العربية السعودية. ويجب أداؤها في شهر ذي الحجة. وهي واجب إلزامي على جميع المسلمين القادرين جسديا وماليا على القيام بالرحلة مرة واحدة على الأقل في حياتهم، وهو يرمز إلى الوحدة الكاملة والمساواة.</p>\n                "
    }
  },
  {
    "id": 2,
    "title": {
      "en": "How to Become a Muslim",
      "bn": "কিভাবে মুসলিম হওয়া যায়",
      "ar": "كيف تصبح مسلما"
    },
    "body": {
      "en": "\n                    <h4>The Meaning of Accepting Islam</h4>\n                    <p>Becoming a Muslim means willingly submitting to Allah and acknowledging Muhammad (ﷺ) as His final messenger. The process is simple, beautiful, and does not require any specialized ceremony or priest.</p>\n                    \n                    <h4>The Step-by-Step Process</h4>\n                    <ol>\n                        <li><strong>Belief in the Heart:</strong> You must genuinely believe that there is only one God (Allah) worthy of worship and that Muhammad (ﷺ) is His final messenger.</li>\n                        <li><strong>Saying the Shahada:</strong> You must declare your faith verbally by reciting the Shahada. It is recommended, though not strictly required, to do this in front of witnesses (like your local Mosque Imam or Muslim friends).</li>\n                        <li><strong>Purification (Ghusl):</strong> After accepting Islam, it is a strongly recommended Sunnah to take a full-body ritual bath (Ghusl) to symbolize physical and spiritual purification.</li>\n                    </ol>\n\n                    <h4>Required Declarations (The Shahada)</h4>\n                    <p>To enter the fold of Islam, one recites the First Kalimah and the Second Kalimah.</p>\n                    \n                    <h5>First Kalimah (Tayyabah - Purity)</h5>\n                    <div class=\"tutorial-arabic\">لَا إِلٰهَ إِلَّا اللّٰهُ مُحَمَّدٌ رَسُولُ اللّٰهِ</div>\n                    <div class=\"tutorial-pronunciation\">🔊 La ilaha illallah, Muhammadur Rasulullah</div>\n                    <p>\"There is no god but Allah, Muhammad is the Messenger of Allah.\"</p>\n\n                    <h5>Second Kalimah (Shahadah - Testimony)</h5>\n                    <div class=\"tutorial-arabic\">أَشْهَدُ أَنْ لَا إِلٰهَ إِلَّا اللّٰهُ وَحْدَهُ لَا شَرِيكَ لَهُ، وَأَشْهَدُ أَنَّ مُحَمَّدًا عَبْدُهُ وَرَسُولُهُ</div>\n                    <div class=\"tutorial-pronunciation\">🔊 Ash-hadu an la ilaha illallahu wahdahu la sharika lahu, wa ash-hadu anna Muhammadan 'abduhu wa rasuluh</div>\n                    <p>\"I bear witness that there is no god but Allah alone, without partner; and I bear witness that Muhammad is His servant and Messenger.\"</p>\n                ",
      "bn": "\n                    <h4>ইসলাম গ্রহণের তাৎপর্য</h4>\n                    <p>মুসলিম হওয়া মানে স্বেচ্ছায় আল্লাহর কাছে আত্মসমর্পণ করা এবং মুহাম্মাদ (সাঃ)-কে তাঁর চূড়ান্ত রসূল হিসেবে স্বীকার করা। প্রক্রিয়াটি সহজ, সুন্দর এবং কোন বিশেষ অনুষ্ঠান বা পুরোহিতের প্রয়োজন নেই।</p>\n                    \n                    <h4>ধাপে ধাপে প্রক্রিয়া</h4>\n                    <ol>\n                        <li><strong>অন্তরে বিশ্বাস:</strong> আপনাকে অবশ্যই সত্যিকার অর্থে বিশ্বাস করতে হবে যে উপাসনার যোগ্য একমাত্র ঈশ্বর (আল্লাহ) এবং মুহাম্মাদ (ﷺ) তাঁর চূড়ান্ত রসূল।</li>\n                        <li><strong>শাহাদা বলা:</strong> শাহাদা পাঠ করে আপনার ঈমানকে মৌখিকভাবে ঘোষণা করতে হবে। এটি সুপারিশ করা হয়, যদিও কঠোরভাবে প্রয়োজন হয় না, এটি সাক্ষীদের সামনে (যেমন আপনার স্থানীয় মসজিদের ইমাম বা মুসলিম বন্ধুদের) করার জন্য।</li>\n                        <li><strong>শুদ্ধিকরণ (গোসল):</strong> ইসলাম গ্রহণের পর, দৈহিক ও আধ্যাত্মিক পরিশুদ্ধির প্রতীক হিসেবে পূর্ণ-শরীরের আনুষ্ঠানিক গোসল (গোসল) করা একটি দৃঢ়ভাবে সুপারিশ করা সুন্নত।</li>\n                    </ol>\n\n                    <h4>প্রয়োজনীয় ঘোষণা (শাহাদা)</h4>\n                    <p>ইসলামে প্রবেশের জন্য প্রথম কালিমা এবং দ্বিতীয় কালেমা পাঠ করা হয়।</p>\n                    \n                    <h5>প্রথম কালিমা (তৈয়্যবাহ - পবিত্রতা)</h5>\n                    <div class=\"tutorial-arabic\">لَا إِلٰهَ إِلَّا اللّٰهُ مُحَمَّدٌ رَسُولُ اللّٰهِ</div>\n                    <div class=\"tutorial-pronunciation\">🔊 La ilaha illallah, Muhammadur Rasulullah</div>\n                    <p>\"আল্লাহ ছাড়া কোন উপাস্য নেই, মুহাম্মদ আল্লাহর রাসূল।\"</p>\n\n                    <h5>দ্বিতীয় কালিমা (শাহাদাহ - সাক্ষ্য)</h5>\n                    <div class=\"tutorial-arabic\">أَشْهَدُ أَنْ لَا إِلٰهَ إِلَّا اللّٰهُ وَحْدَهُ لَا شَرِيكَ لَهُ، وَأَشْهَدُ أَنَّ مُحَمَّدًا عَبْدُهُ وَرَسُولُهُ</div>\n                    <div class=\"tutorial-pronunciation\">🔊 Ash-hadu an la ilaha illallahu wahdahu la sharika lahu, wa ash-hadu anna Muhammadan 'abduhu wa rasuluh</div>\n                    <p>\"আমি সাক্ষ্য দিচ্ছি যে, একমাত্র আল্লাহ ছাড়া কোন উপাস্য নেই, শরীক নেই; এবং আমি সাক্ষ্য দিচ্ছি যে মুহাম্মদ তাঁর বান্দা ও রাসূল।\"</p>\n                ",
      "ar": "\n                    <h4>معنى قبول الإسلام</h4>\n                    <p>أن تصبح مسلماً يعني الاستسلام عن طيب خاطر لله والاعتراف بمحمد (صلى الله عليه وسلم) كرسوله الأخير. العملية بسيطة وجميلة ولا تحتاج إلى أي مراسم أو كاهن متخصص.</p>\n                    \n                    <h4>العملية خطوة بخطوة</h4>\n                    <ol>\n                        <li><strong>الإيمان بالقلب:</strong> يجب أن تؤمن بصدق أن هناك إله واحد فقط (الله) يستحق العبادة وأن محمد (صلى الله عليه وسلم) هو خاتم رسوله.</li>\n                        <li><strong>قول الشهادة:</strong> يجب أن تعلن إيمانك لفظيا من خلال تلاوة الشهادة. يوصى، على الرغم من أنه ليس مطلوبًا بشكل صارم، القيام بذلك أمام الشهود (مثل إمام المسجد المحلي أو الأصدقاء المسلمين).</li>\n                        <li><strong>التطهير (الغسل):</strong> بعد قبول الإسلام، من المستحسن بشدة أن تأخذ حمامًا لكامل الجسم (الغسل) يرمز إلى التطهير الجسدي والروحي.</li>\n                    </ol>\n\n                    <h4>التصريحات المطلوبة (الشهادة)</h4>\n                    <p>للدخول في حظيرة الإسلام يقرأ الكلمة الأولى والكلمة الثانية.</p>\n                    \n                    <h5>الكلمة الأولى (الطيبة - الطهارة)</h5>\n                    <div class=\"tutorial-arabic\">لَا إِلٰهَ إِلَّا اللّٰهُ مُحَمَّدٌ رَسُولُ اللّٰهِ</div>\n                    <div class=\"tutorial-pronunciation\">🔊 La ilaha illallah, Muhammadur Rasulullah</div>\n                    <p>\"لا إله إلا الله محمد رسول الله\".</p>\n\n                    <h5>الكلمة الثانية (الشهادة - الشهادة)</h5>\n                    <div class=\"tutorial-arabic\">أَشْهَدُ أَنْ لَا إِلٰهَ إِلَّا اللّٰهُ وَحْدَهُ لَا شَرِيكَ لَهُ، وَأَشْهَدُ أَنَّ مُحَمَّدًا عَبْدُهُ وَرَسُولُهُ</div>\n                    <div class=\"tutorial-pronunciation\">🔊 Ash-hadu an la ilaha illallahu wahdahu la sharika lahu, wa ash-hadu anna Muhammadan 'abduhu wa rasuluh</div>\n                    <p>\"أشهد أن لا إله إلا الله وحده لا شريك له، وأشهد أن محمداً عبده ورسوله\".</p>\n                "
    }
  },
  {
    "id": 3,
    "title": {
      "en": "The 6 Kalimahs of Islam",
      "bn": "ইসলামের ৬টি কালিমা",
      "ar": "6 كلمات الإسلام"
    },
    "body": {
      "en": "\n                    <p>The Six Kalimahs summarize the core beliefs of a Muslim. They are widely taught for memorization and spiritual reflection.</p>\n                    \n                    <h4>1. First Kalimah (Tayyabah - The Word of Purity)</h4>\n                    <div class=\"tutorial-arabic\">لَا إِلٰهَ إِلَّا اللّٰهُ مُحَمَّدٌ رَسُولُ اللّٰهِ</div>\n                    <div class=\"tutorial-pronunciation\">🔊 La ilaha illallah, Muhammadur Rasulullah</div>\n                    <p>\"There is no god but Allah, Muhammad is the Messenger of Allah.\"</p>\n                    \n                    <h4>2. Second Kalimah (Shahadah - The Word of Testimony)</h4>\n                    <div class=\"tutorial-arabic\">أَشْهَدُ أَنْ لَا إِلٰهَ إِلَّا اللّٰهُ وَحْدَهُ لَا شَرِيكَ لَهُ، وَأَشْهَدُ أَنَّ مُحَمَّدًا عَبْدُهُ وَرَسُولُهُ</div>\n                    <div class=\"tutorial-pronunciation\">🔊 Ash-hadu an la ilaha illallahu wahdahu la sharika lahu, wa ash-hadu anna Muhammadan 'abduhu wa rasuluh</div>\n                    <p>\"I bear witness that there is no god but Allah alone, without partner; and I bear witness that Muhammad is His servant and Messenger.\"</p>\n\n                    <h4>3. Third Kalimah (Tamjeed - The Word of Glorification)</h4>\n                    <div class=\"tutorial-arabic\">سُبْحَانَ اللّٰهِ وَالْحَمْدُ لِلّٰهِ وَلَا إِلٰهَ إِلَّا اللّٰهُ وَاللّٰهُ أَكْبَرُ، وَلَا حَوْلَ وَلَا قُوَّةَ إِلَّا بِاللّٰهِ الْعَلِيِّ الْعَظِيمِ</div>\n                    <div class=\"tutorial-pronunciation\">🔊 Subhanallahi walhamdu lillahi wa la ilaha illallahu wallahu akbar, wa la hawla wa la quwwata illa billahil 'aliyyil 'adheem</div>\n                    <p>\"Glory be to Allah, all praise be to Allah. There is no god but Allah, and Allah is the Greatest. There is no might nor power except in Allah, the Most High, the Supreme.\"</p>\n\n                    <h4>4. Fourth Kalimah (Tawheed - The Word of Oneness)</h4>\n                    <div class=\"tutorial-arabic\">لَا إِلٰهَ إِلَّا اللّٰهُ وَحْدَهُ لَا شَرِيكَ لَهُ، لَهُ الْمُلْكُ وَلَهُ الْحَمْدُ، يُحْيِي وَيُمِيتُ وَهُوَ حَيٌّ لَا يَمُوتُ أَبَدًا أَبَدًا، ذُو الْجَلَالِ وَالْإِكْرَامِ، بِيَدِهِ الْخَيْرُ، وَهُوَ عَلَىٰ كُلِّ شَيْءٍ قَدِيرٌ</div>\n                    <div class=\"tutorial-pronunciation\">🔊 La ilaha illallahu wahdahu la sharika lahu, lahul-mulku wa lahul-hamdu, yuhyi wa yumitu wa huwa hayyun la yamutu abadan abada, dhul jalali wal-ikram, bi-yadihil-khayr, wa huwa 'ala kulli shay'in qadeer</div>\n                    <p>\"There is no god but Allah alone, He has no partner. To Him belongs the dominion, and to Him belongs all praise. He gives life and causes death, and He is Ever-Living, He never dies. Possessor of Majesty and Honor, in His Hand is all good, and He has power over all things.\"</p>\n\n                    <h4>5. Fifth Kalimah (Astaghfar - The Word of Penitence)</h4>\n                    <div class=\"tutorial-arabic\">أَسْتَغْفِرُ اللّٰهَ رَبِّي مِنْ كُلِّ ذَنْبٍ أَذْنَبْتُهُ عَمْدًا أَوْ خَطَأً، سِرًّا أَوْ عَلَانِيَةً، وَأَتُوبُ إِلَيْهِ مِنَ الذَّنْبِ الَّذِي أَعْلَمُ، وَمِنَ الذَّنْبِ الَّذِي لَا أَعْلَمُ، إِنَّكَ أَنْتَ عَلَّامُ الْغُيُوبِ وَسَتَّارُ الْعُيُوبِ وَغَفَّارُ الذُّنُوبِ، وَلَا حَوْلَ وَلَا قُوَّةَ إِلَّا بِاللّٰهِ الْعَلِيِّ الْعَظِيمِ</div>\n                    <div class=\"tutorial-pronunciation\">🔊 Astaghfirullaha rabbi min kulli dhanbin adhnabtuhu 'amdan aw khata'an sirran aw 'alaniyata, wa atubu ilayhi minadh-dhanbilladhi a'lamu wa minadh-dhanbilladhi la a'lamu, innaka anta 'allamul-ghuyub wa sattarul-'uyub wa ghaffarudh-dhunub, wa la hawla wa la quwwata illa billahil 'aliyyil 'adheem</div>\n                    <p>\"I seek forgiveness from Allah, my Lord, for every sin I committed intentionally or by mistake, in secret or in public. I turn in repentance to Him from the sin that I know, and from the sin that I do not know. Indeed, You are the Knower of the unseen, the Concealer of faults, and the Forgiver of sins. There is no might nor power except in Allah, the Most High, the Supreme.\"</p>\n\n                    <h4>6. Sixth Kalimah (Radde Kufr - The Word of Rejecting Disbelief)</h4>\n                    <div class=\"tutorial-arabic\">اَللّٰهُمَّ إِنِّي أَعُوذُ بِكَ مِنْ أَنْ أُشْرِكَ بِكَ شَيْئًا وَأَنَا أَعْلَمُ بِهِ، وَأَسْتَغْفِرُكَ لِمَا لَا أَعْلَمُ بِهِ، تُبْتُ عَنْهُ وَتَبَرَّأْتُ مِنَ الْكُفْرِ وَالشِّرْكِ وَالْكِذْبِ وَالْغِيبَةِ وَالْبِدْعَةِ وَالنَّمِيمَةِ وَالْفَوَاحِشِ وَالْبُهْتَانِ وَالْمَعَاصِي كُلِّهَا، وَأَسْلَمْتُ وَأَقُولُ: لَا إِلٰهَ إِلَّا اللّٰهُ مُحَمَّدٌ رَسُولُ اللّٰهِ</div>\n                    <div class=\"tutorial-pronunciation\">🔊 Allahumma inni a'udhu bika min an ushrika bika shay'an wa ana a'lamu bihi, wa astaghfiruka lima la a'lamu bihi, tubtu 'anhu wa tabarra'tu minal-kufri wash-shirki wal-kidhbi wal-ghibati wal-bid'ati wan-namimati wal-fawahishi wal-buhtani wal-ma'asi kulliha, wa aslamtu wa aqulu: la ilaha illallah, Muhammadur Rasulullah</div>\n                    <p>\"O Allah! I seek refuge in You from knowingly associating anything with You, and I seek Your forgiveness for what I do not know. I repent from it and I free myself from disbelief, polytheism, falsehood, backbiting, innovation, tale-bearing, shameful deeds, slander, and all forms of disobedience. I submit to Your will and I declare: There is no god but Allah, Muhammad is the Messenger of Allah.\"</p>\n                ",
      "bn": "\n                    <p>ছয়টি কালিমা একজন মুসলমানের মূল বিশ্বাসকে সংক্ষিপ্ত করে। তারা ব্যাপকভাবে মুখস্থ এবং আধ্যাত্মিক প্রতিফলন জন্য শেখানো হয়.</p>\n                    \n                    <h4>1. প্রথম কালিমা (তৈয়্যবাহ - পবিত্রতার শব্দ)</h4>\n                    <div class=\"tutorial-arabic\">لَا إِلٰهَ إِلَّا اللّٰهُ مُحَمَّدٌ رَسُولُ اللّٰهِ</div>\n                    <div class=\"tutorial-pronunciation\">🔊 La ilaha illallah, Muhammadur Rasulullah</div>\n                    <p>\"আল্লাহ ছাড়া কোন উপাস্য নেই, মুহাম্মদ আল্লাহর রাসূল।\"</p>\n                    \n                    <h4>2. দ্বিতীয় কালিমা (শাহাদাহ - সাক্ষ্যের শব্দ)</h4>\n                    <div class=\"tutorial-arabic\">أَشْهَدُ أَنْ لَا إِلٰهَ إِلَّا اللّٰهُ وَحْدَهُ لَا شَرِيكَ لَهُ، وَأَشْهَدُ أَنَّ مُحَمَّدًا عَبْدُهُ وَرَسُولُهُ</div>\n                    <div class=\"tutorial-pronunciation\">🔊 Ash-hadu an la ilaha illallahu wahdahu la sharika lahu, wa ash-hadu anna Muhammadan 'abduhu wa rasuluh</div>\n                    <p>\"আমি সাক্ষ্য দিচ্ছি যে, একমাত্র আল্লাহ ছাড়া কোন উপাস্য নেই, শরীক নেই; এবং আমি সাক্ষ্য দিচ্ছি যে মুহাম্মদ তাঁর বান্দা ও রাসূল।\"</p>\n\n                    <h4>3. তৃতীয় কালিমা (তামজিদ - গৌরবের শব্দ)</h4>\n                    <div class=\"tutorial-arabic\">سُبْحَانَ اللّٰهِ وَالْحَمْدُ لِلّٰهِ وَلَا إِلٰهَ إِلَّا اللّٰهُ وَاللّٰهُ أَكْبَرُ، وَلَا حَوْلَ وَلَا قُوَّةَ إِلَّا بِاللّٰهِ الْعَلِيِّ الْعَظِيمِ</div>\n                    <div class=\"tutorial-pronunciation\">🔊 Subhanallahi walhamdu lillahi wa la ilaha illallahu wallahu akbar, wa la hawla wa la quwwata illa billahil 'aliyyil 'adheem</div>\n                    <p>\"আল্লাহ পবিত্র, সকল প্রশংসা আল্লাহর জন্য। আল্লাহ ছাড়া কোন উপাস্য নেই, এবং আল্লাহ সর্বশ্রেষ্ঠ। আল্লাহ ছাড়া কোন শক্তি বা ক্ষমতা নেই, সর্বোচ্চ, সর্বোচ্চ।\"</p>\n\n                    <h4>4. চতুর্থ কালিমা (তাওহীদ - একত্বের শব্দ)</h4>\n                    <div class=\"tutorial-arabic\">لَا إِلٰهَ إِلَّا اللّٰهُ وَحْدَهُ لَا شَرِيكَ لَهُ، لَهُ الْمُلْكُ وَلَهُ الْحَمْدُ، يُحْيِي وَيُمِيتُ وَهُوَ حَيٌّ لَا يَمُوتُ أَبَدًا أَبَدًا، ذُو الْجَلَالِ وَالْإِكْرَامِ، بِيَدِهِ الْخَيْرُ، وَهُوَ عَلَىٰ كُلِّ شَيْءٍ قَدِيرٌ</div>\n                    <div class=\"tutorial-pronunciation\">🔊 La ilaha illallahu wahdahu la sharika lahu, lahul-mulku wa lahul-hamdu, yuhyi wa yumitu wa huwa hayyun la yamutu abadan abada, dhul jalali wal-ikram, bi-yadihil-khayr, wa huwa 'ala kulli shay'in qadeer</div>\n                    <p>\"আল্লাহ ছাড়া কোন উপাস্য নেই, তাঁর কোন শরীক নেই। রাজত্ব তাঁরই, এবং সকল প্রশংসা তাঁরই। তিনি জীবন দান করেন এবং মৃত্যু ঘটান এবং তিনি চিরজীবী, তিনি কখনই মৃত্যুবরণ করেন না। মহিমা ও মর্যাদার অধিকারী, তাঁর হাতেই সবকিছু রয়েছে এবং তিনি সব কিছুর উপর ক্ষমতাবান।\"</p>\n\n                    <h4>5. পঞ্চম কালিমা (আস্তাগফার - অনুতাপের শব্দ)</h4>\n                    <div class=\"tutorial-arabic\">أَسْتَغْفِرُ اللّٰهَ رَبِّي مِنْ كُلِّ ذَنْبٍ أَذْنَبْتُهُ عَمْدًا أَوْ خَطَأً، سِرًّا أَوْ عَلَانِيَةً، وَأَتُوبُ إِلَيْهِ مِنَ الذَّنْبِ الَّذِي أَعْلَمُ، وَمِنَ الذَّنْبِ الَّذِي لَا أَعْلَمُ، إِنَّكَ أَنْتَ عَلَّامُ الْغُيُوبِ وَسَتَّارُ الْعُيُوبِ وَغَفَّارُ الذُّنُوبِ، وَلَا حَوْلَ وَلَا قُوَّةَ إِلَّا بِاللّٰهِ الْعَلِيِّ الْعَظِيمِ</div>\n                    <div class=\"tutorial-pronunciation\">🔊 Astaghfirullaha rabbi min kulli dhanbin adhnabtuhu 'amdan aw khata'an sirran aw 'alaniyata, wa atubu ilayhi minadh-dhanbilladhi a'lamu wa minadh-dhanbilladhi la a'lamu, innaka anta 'allamul-ghuyub wa sattarul-'uyub wa ghaffarudh-dhunub, wa la hawla wa la quwwata illa billahil 'aliyyil 'adheem</div>\n                    <p>\"আমি আল্লাহর কাছে ক্ষমা চাই, আমার পালনকর্তা, আমি ইচ্ছাকৃতভাবে বা ভুলবশত, গোপনে বা প্রকাশ্যে করেছি এমন প্রতিটি পাপের জন্য। আমি যে পাপ জানি এবং যে পাপ আমি জানি না তা থেকে আমি তাঁর কাছে অনুতপ্ত হই। প্রকৃতপক্ষে, আপনি অদৃশ্যের জ্ঞানী, ত্রুটিগুলি গোপনকারী এবং পরম ক্ষমাশীল, মহান আল্লাহ ছাড়া কোন ক্ষমতা নেই।\"</p>\n\n                    <h4>6. ষষ্ঠ কালিমা (রাদ্দে কুফর - অবিশ্বাস প্রত্যাখ্যানের বাণী)</h4>\n                    <div class=\"tutorial-arabic\">اَللّٰهُمَّ إِنِّي أَعُوذُ بِكَ مِنْ أَنْ أُشْرِكَ بِكَ شَيْئًا وَأَنَا أَعْلَمُ بِهِ، وَأَسْتَغْفِرُكَ لِمَا لَا أَعْلَمُ بِهِ، تُبْتُ عَنْهُ وَتَبَرَّأْتُ مِنَ الْكُفْرِ وَالشِّرْكِ وَالْكِذْبِ وَالْغِيبَةِ وَالْبِدْعَةِ وَالنَّمِيمَةِ وَالْفَوَاحِشِ وَالْبُهْتَانِ وَالْمَعَاصِي كُلِّهَا، وَأَسْلَمْتُ وَأَقُولُ: لَا إِلٰهَ إِلَّا اللّٰهُ مُحَمَّدٌ رَسُولُ اللّٰهِ</div>\n                    <div class=\"tutorial-pronunciation\">🔊 Allahumma inni a'udhu bika min an ushrika bika shay'an wa ana a'lamu bihi, wa astaghfiruka lima la a'lamu bihi, tubtu 'anhu wa tabarra'tu minal-kufri wash-shirki wal-kidhbi wal-ghibati wal-bid'ati wan-namimati wal-fawahishi wal-buhtani wal-ma'asi kulliha, wa aslamtu wa aqulu: la ilaha illallah, Muhammadur Rasulullah</div>\n                    <p>\"হে আল্লাহ! আমি জেনেশুনে আপনার সাথে কোন কিছুকে শরীক করা থেকে আপনার কাছে আশ্রয় চাই, এবং আমি যা জানি না তার জন্য আমি আপনার কাছে ক্ষমা চাই। আমি তা থেকে তওবা করি এবং আমি নিজেকে কুফর, শিরক, মিথ্যা, গীবত, বিদআত, গল্প বলা, লজ্জাজনক কাজ, অপবাদ এবং সকল প্রকার অবাধ্যতা থেকে নিজেকে মুক্ত করি, কিন্তু আমি ঘোষণা করি না যে, আমি ঘোষণা করি যে, আমি মুহাম্মাদকে স্বীকার করব না। আল্লাহর রাসূল।\"</p>\n                ",
      "ar": "\n                    <p>تلخص الكلمات الستة المعتقدات الأساسية للمسلم. يتم تدريسها على نطاق واسع للحفظ والتأمل الروحي.</p>\n                    \n                    <h4>1. الكلمة الأولى (الطيبة – كلمة الطهارة)</h4>\n                    <div class=\"tutorial-arabic\">لَا إِلٰهَ إِلَّا اللّٰهُ مُحَمَّدٌ رَسُولُ اللّٰهِ</div>\n                    <div class=\"tutorial-pronunciation\">🔊 La ilaha illallah, Muhammadur Rasulullah</div>\n                    <p>\"لا إله إلا الله محمد رسول الله\".</p>\n                    \n                    <h4>2. الكلمة الثانية (الشهادة – كلمة الشهادة)</h4>\n                    <div class=\"tutorial-arabic\">أَشْهَدُ أَنْ لَا إِلٰهَ إِلَّا اللّٰهُ وَحْدَهُ لَا شَرِيكَ لَهُ، وَأَشْهَدُ أَنَّ مُحَمَّدًا عَبْدُهُ وَرَسُولُهُ</div>\n                    <div class=\"tutorial-pronunciation\">🔊 Ash-hadu an la ilaha illallahu wahdahu la sharika lahu, wa ash-hadu anna Muhammadan 'abduhu wa rasuluh</div>\n                    <p>\"أشهد أن لا إله إلا الله وحده لا شريك له، وأشهد أن محمداً عبده ورسوله\".</p>\n\n                    <h4>3. الكلمة الثالثة (التمجيد – كلمة التسبيح)</h4>\n                    <div class=\"tutorial-arabic\">سُبْحَانَ اللّٰهِ وَالْحَمْدُ لِلّٰهِ وَلَا إِلٰهَ إِلَّا اللّٰهُ وَاللّٰهُ أَكْبَرُ، وَلَا حَوْلَ وَلَا قُوَّةَ إِلَّا بِاللّٰهِ الْعَلِيِّ الْعَظِيمِ</div>\n                    <div class=\"tutorial-pronunciation\">🔊 Subhanallahi walhamdu lillahi wa la ilaha illallahu wallahu akbar, wa la hawla wa la quwwata illa billahil 'aliyyil 'adheem</div>\n                    <p>\"سبحان الله والحمد لله ولا إله إلا الله والله أكبر ولا حول ولا قوة إلا بالله العلي العظيم.\"</p>\n\n                    <h4>4. الكلمة الرابعة (التوحيد – كلمة الوحدانية)</h4>\n                    <div class=\"tutorial-arabic\">لَا إِلٰهَ إِلَّا اللّٰهُ وَحْدَهُ لَا شَرِيكَ لَهُ، لَهُ الْمُلْكُ وَلَهُ الْحَمْدُ، يُحْيِي وَيُمِيتُ وَهُوَ حَيٌّ لَا يَمُوتُ أَبَدًا أَبَدًا، ذُو الْجَلَالِ وَالْإِكْرَامِ، بِيَدِهِ الْخَيْرُ، وَهُوَ عَلَىٰ كُلِّ شَيْءٍ قَدِيرٌ</div>\n                    <div class=\"tutorial-pronunciation\">🔊 La ilaha illallahu wahdahu la sharika lahu, lahul-mulku wa lahul-hamdu, yuhyi wa yumitu wa huwa hayyun la yamutu abadan abada, dhul jalali wal-ikram, bi-yadihil-khayr, wa huwa 'ala kulli shay'in qadeer</div>\n                    <p>\"لا إله إلا الله وحده لا شريك له، له الملك وله الحمد، يحيي ويميت، وهو حي لا يموت، ذو الجلال والإكرام، بيده الخير، وهو على كل شيء قدير\".</p>\n\n                    <h4>5. الكلمة الخامسة (الاستغفار – كلمة التوبة)</h4>\n                    <div class=\"tutorial-arabic\">أَسْتَغْفِرُ اللّٰهَ رَبِّي مِنْ كُلِّ ذَنْبٍ أَذْنَبْتُهُ عَمْدًا أَوْ خَطَأً، سِرًّا أَوْ عَلَانِيَةً، وَأَتُوبُ إِلَيْهِ مِنَ الذَّنْبِ الَّذِي أَعْلَمُ، وَمِنَ الذَّنْبِ الَّذِي لَا أَعْلَمُ، إِنَّكَ أَنْتَ عَلَّامُ الْغُيُوبِ وَسَتَّارُ الْعُيُوبِ وَغَفَّارُ الذُّنُوبِ، وَلَا حَوْلَ وَلَا قُوَّةَ إِلَّا بِاللّٰهِ الْعَلِيِّ الْعَظِيمِ</div>\n                    <div class=\"tutorial-pronunciation\">🔊 Astaghfirullaha rabbi min kulli dhanbin adhnabtuhu 'amdan aw khata'an sirran aw 'alaniyata, wa atubu ilayhi minadh-dhanbilladhi a'lamu wa minadh-dhanbilladhi la a'lamu, innaka anta 'allamul-ghuyub wa sattarul-'uyub wa ghaffarudh-dhunub, wa la hawla wa la quwwata illa billahil 'aliyyil 'adheem</div>\n                    <p>\"أستغفر الله ربي من كل ذنب أذنبته عمدا أو خطأ، في سر أو علانية، أتوب إليه من الذنب الذي أعلمه، ومن الذنب الذي لا أعلمه، إنك علام الغيب، وستره، وغفار الذنوب، ولا حول ولا قوة إلا بالله العلي العظيم\".</p>\n\n                    <h4>6. الكلمة السادسة (رد الكفر – كلمة رفض الكفر)</h4>\n                    <div class=\"tutorial-arabic\">اَللّٰهُمَّ إِنِّي أَعُوذُ بِكَ مِنْ أَنْ أُشْرِكَ بِكَ شَيْئًا وَأَنَا أَعْلَمُ بِهِ، وَأَسْتَغْفِرُكَ لِمَا لَا أَعْلَمُ بِهِ، تُبْتُ عَنْهُ وَتَبَرَّأْتُ مِنَ الْكُفْرِ وَالشِّرْكِ وَالْكِذْبِ وَالْغِيبَةِ وَالْبِدْعَةِ وَالنَّمِيمَةِ وَالْفَوَاحِشِ وَالْبُهْتَانِ وَالْمَعَاصِي كُلِّهَا، وَأَسْلَمْتُ وَأَقُولُ: لَا إِلٰهَ إِلَّا اللّٰهُ مُحَمَّدٌ رَسُولُ اللّٰهِ</div>\n                    <div class=\"tutorial-pronunciation\">🔊 Allahumma inni a'udhu bika min an ushrika bika shay'an wa ana a'lamu bihi, wa astaghfiruka lima la a'lamu bihi, tubtu 'anhu wa tabarra'tu minal-kufri wash-shirki wal-kidhbi wal-ghibati wal-bid'ati wan-namimati wal-fawahishi wal-buhtani wal-ma'asi kulliha, wa aslamtu wa aqulu: la ilaha illallah, Muhammadur Rasulullah</div>\n                    <p>\"اللهم إني أعوذ بك من أن أشرك بك وأنا أعلم، وأستغفرك لما لا أعلم، وأتوب منه وأبرأ من الكفر والشرك والكذب والغيبة والبدع والنميمة والفحشاء والقذف، وجميع أنواع المعاصي، وأسلمت لأمرك وأشهد: لا إله إلا الله، محمد رسول الله\".</p>\n                "
    }
  },
  {
    "id": 13,
    "title": {
      "en": "Zakat (Almsgiving)",
      "bn": "যাকাত (দান)",
      "ar": "الزكاة (الصدقة)"
    },
    "body": {
      "en": "\n                    <h4>1. Meaning and Importance</h4>\n                    <p>Zakat is the third pillar of Islam. It is a mandatory charitable contribution that purifies wealth and maintains economic balance.</p>\n                    <blockquote class=\"tutorial-reference\">\n                        <p>\"And establish prayer and give Zakat and bow with those who bow [in worship and obedience].\" (Quran 2:43)</p>\n                    </blockquote>\n                    \n                    <h4>2. Who Must Pay Zakat?</h4>\n                    <p>Zakat is obligatory for every sane, adult Muslim who possesses wealth above a minimum threshold (Nisab) for one full lunar year.</p>\n                    \n                    <h4>3. The Recipients of Zakat</h4>\n                    <p>According to the Quran (9:60), there are eight categories of people eligible to receive Zakat:</p>\n                    <ul>\n                        <li>1. The Poor (Al-Fuqara)</li>\n                        <li>2. The Needy (Al-Masakin)</li>\n                        <li>3. Zakat Administrators</li>\n                        <li>4. Those whose hearts are to be reconciled</li>\n                        <li>5. To free those in bondage/slaves</li>\n                        <li>6. Those in debt</li>\n                        <li>7. In the cause of Allah</li>\n                        <li>8. The wayfarer (travelers)</li>\n                    </ul>\n\n                    <h4>4. Warning against Neglect</h4>\n                    <p>The Prophet ﷺ said: <em>\"Whoever is given wealth by Allah and does not pay Zakat on it, on the Day of Resurrection his wealth will be made to appear to him as a bald-headed poisonous snake... it will circle his neck and bite his cheeks and say, 'I am your wealth, I am your treasure.'\"</em> (Sahih Bukhari 1403)</p>\n                ",
      "bn": "\n                    <h4>1. অর্থ এবং গুরুত্ব</h4>\n                    <p>যাকাত ইসলামের তৃতীয় স্তম্ভ। এটি একটি বাধ্যতামূলক দাতব্য অবদান যা সম্পদকে বিশুদ্ধ করে এবং অর্থনৈতিক ভারসাম্য বজায় রাখে।</p>\n                    <blockquote class=\"tutorial-reference\">\n                        <p>\"আর নামায কায়েম কর, যাকাত দাও এবং রুকুকারীদের সাথে রুকু কর।\" (কুরআন 2:43)</p>\n                    </blockquote>\n                    \n                    <h4>2. কাদের জাকাত দিতে হবে?</h4>\n                    <p>জাকাত প্রত্যেক বিবেকবান, প্রাপ্তবয়স্ক মুসলমানের জন্য বাধ্যতামূলক, যার ন্যূনতম প্রান্তিকের (নিসাব) এক পূর্ণ চান্দ্র বছরের জন্য সম্পদ রয়েছে।</p>\n                    \n                    <h4>3. যাকাত প্রাপক</h4>\n                    <p>কুরআন (9:60) অনুসারে, জাকাত পাওয়ার যোগ্য আট শ্রেণীর লোক রয়েছে:</p>\n                    <ul>\n                        <li>1. দরিদ্র (আল-ফুকারা)</li>\n                        <li>2. অভাবী (আল-মাসাকিন)</li>\n                        <li>3. যাকাত প্রশাসক</li>\n                        <li>4. যাদের অন্তরে মিলিত হতে হবে</li>\n                        <li>5. দাস/দাসীদের মুক্ত করা</li>\n                        <li>6. যারা ঋণী</li>\n                        <li>7. আল্লাহর পথে</li>\n                        <li>8. পথিক (যাত্রী)</li>\n                    </ul>\n\n                    <h4>4. অবহেলার বিরুদ্ধে সতর্কতা</h4>\n                    <p>নবী সাল্লাল্লাহু আলাইহি ওয়াসাল্লাম বলেছেনঃ <em>\"আল্লাহ যাকে ধন-সম্পদ দান করেন এবং তাতে যাকাত দেন না, কিয়ামতের দিন তার সম্পদ তার কাছে একটি টাক মাথাওয়ালা বিষধর সাপের মতো দেখাবে... এটি তার ঘাড় প্রদক্ষিণ করবে এবং তার গালে কামড় দেবে এবং বলবে, আমি তোমার সম্পদ, আমি তোমার ধন।\"</em> (সহীহ বুখারী 1403)</p>\n                ",
      "ar": "\n                    <h4>1. المعنى والأهمية</h4>\n                    <p>الزكاة هي الركن الثالث من أركان الإسلام. وهي مساهمة خيرية إلزامية تنقي الثروة وتحافظ على التوازن الاقتصادي.</p>\n                    <blockquote class=\"tutorial-reference\">\n                        <p>\"وأقيموا الصلاة وآتوا الزكاة واركعوا مع الراكعين\". (القرآن 2:43)</p>\n                    </blockquote>\n                    \n                    <h4>2. على من يجب عليه دفع الزكاة؟</h4>\n                    <p>تجب الزكاة على كل مسلم بالغ عاقل يملك مالاً يزيد على النصاب عن سنة قمرية كاملة.</p>\n                    \n                    <h4>3. مستلمو الزكاة</h4>\n                    <p>وفقا للقرآن (9:60)، هناك ثماني فئات من الأشخاص الذين يحق لهم الحصول على الزكاة:</p>\n                    <ul>\n                        <li>1. الفقراء (الفقراء)</li>\n                        <li>2. المحتاج (المساكن)</li>\n                        <li>3. مأمورو الزكاة</li>\n                        <li>4.المصالحة قلوبهم</li>\n                        <li>5. لتحرير من هم في العبودية / العبيد</li>\n                        <li>6. المدينون</li>\n                        <li>7. في سبيل الله</li>\n                        <li>8. السبيل (المسافرون)</li>\n                    </ul>\n\n                    <h4>4. التحذير من الإهمال</h4>\n                    <p>قال النبي ﷺ : <em>«من آتاه الله مالاً ولم يؤد زكاته، مثل له ماله يوم القيامة كالحية الأقرع، فتطوق رقبته، وتعض خديه، وتقول: أنا مالك، أنا كنزك».</em> (صحيح البخاري ١٤٠٣)</p>\n                "
    }
  },
  {
    "id": 14,
    "title": {
      "en": "Guide to Fasting in Ramadan",
      "bn": "রমজানে রোজা রাখার নির্দেশিকা",
      "ar": "دليل الصيام في رمضان"
    },
    "body": {
      "en": "\n                    <h4>What is Sawm?</h4>\n                    <p>Fasting from dawn (Fajr) to sunset (Maghrib), abstaining from food, drink, smoking, and marital relations. (Quran 2:183)</p>\n                    \n                    <h4>Niyyah (Intention) for Starting the Fast</h4>\n                    <div class=\"tutorial-arabic\">نَوَيْتُ أَنْ أَصُومَ غَدًا مِنْ شَهْرِ رَمَضَانَ الْمُبَارَكِ فَرْضًا لِلَّهِ تَعَالَى</div>\n                    <div class=\"tutorial-pronunciation\">🔊 Nawaytu an asuma ghadan min shahri ramadanal mubarak fardhan lillahi ta'ala</div>\n                    <p>\"I intend to fast tomorrow for the blessed month of Ramadan as an obligation for Allah, the Most High.\"</p>\n\n                    <h4>Dua for Iftar (Breaking the Fast)</h4>\n                    <h5>Common/Extended Dua:</h5>\n                    <div class=\"tutorial-arabic\">اللَّهُمَّ إِنِّي لَكَ صُمْتُ وَبِكَ آمَنْتُ وَعَلَى رِزْقِكَ أَفْطَرْتُ بِرَحْمَتِكَ يَا أَرْحَمَ الرَّاحِمِينَ</div>\n                    <div class=\"tutorial-pronunciation\">🔊 Allahumma inni laka sumtu, wa bika aamantu, wa 'ala rizqika aftartu, birahmatika ya Arhamar Raahimeen</div>\n                    <p>\"O Allah, for You I have fasted, in You I believe, and with Your provision I break my fast. By Your mercy, O Most Merciful of the merciful.\"</p>\n\n                    <h5>Sunnah Dua:</h5>\n                    <div class=\"tutorial-arabic\">ذَهَبَ الظَّمَأُ وَابْتَلَّتِ الْعُرُوقُ وَثَبَتَ الْأَجْرُ إِنْ شَاءَ اللَّهُ</div>\n                    <div class=\"tutorial-pronunciation\">🔊 Dhahaba adh-dhama'u wabtallatil-'uruqu wa thabatal-ajru in sha Allah</div>\n                    <p>\"The thirst has gone, the veins are moistened, and the reward is assured, if Allah wills.\" (Sunan Abi Dawud 2357)</p>\n\n                    <h4>Suhoor (Pre-Dawn Meal)</h4>\n                    <p>The Prophet ﷺ said: <em>\"Take suhoor, for indeed there is blessing in suhoor.\"</em> (Sahih Bukhari 1923 & Sahih Muslim 1095)</p>\n\n                    <h4>Who is Exempt?</h4>\n                    <p>(Based on Quran 2:184-185)</p>\n                    <ul>\n                        <li>The sick or on medication</li>\n                        <li>Travelers</li>\n                        <li>Pregnant, breastfeeding, or menstruating women</li>\n                        <li>The elderly who cannot fast</li>\n                        <li>Children before puberty</li>\n                    </ul>\n                ",
      "bn": "\n                    <h4>সাওম কি?</h4>\n                    <p>ভোর (ফজর) থেকে সূর্যাস্ত (মাগরিব) পর্যন্ত রোজা রাখা, খাদ্য, পানীয়, ধূমপান এবং বৈবাহিক সম্পর্ক থেকে বিরত থাকা। (কুরআন 2:183)</p>\n                    \n                    <h4>রোজা শুরু করার নিয়্যাহ</h4>\n                    <div class=\"tutorial-arabic\">نَوَيْتُ أَنْ أَصُومَ غَدًا مِنْ شَهْرِ رَمَضَانَ الْمُبَارَكِ فَرْضًا لِلَّهِ تَعَالَى</div>\n                    <div class=\"tutorial-pronunciation\">🔊 Nawaytu an asuma ghadan min shahri ramadanal mubarak fardhan lillahi ta'ala</div>\n                    <p>\"আমি আগামীকাল রমজানের বরকতময় মাসের জন্য রোজা রাখার ইচ্ছা করছি, মহান আল্লাহর জন্য একটি বাধ্যবাধকতা হিসাবে।\"</p>\n\n                    <h4>ইফতারের জন্য দুআ (রোজা ভাঙা)</h4>\n                    <h5>সাধারণ/বর্ধিত দুআ:</h5>\n                    <div class=\"tutorial-arabic\">اللَّهُمَّ إِنِّي لَكَ صُمْتُ وَبِكَ آمَنْتُ وَعَلَى رِزْقِكَ أَفْطَرْتُ بِرَحْمَتِكَ يَا أَرْحَمَ الرَّاحِمِينَ</div>\n                    <div class=\"tutorial-pronunciation\">🔊 Allahumma inni laka sumtu, wa bika aamantu, wa 'ala rizqika aftartu, birahmatika ya Arhamar Raahimeen</div>\n                    <p>\"হে আল্লাহ, তোমার জন্য আমি রোজা রেখেছি, তোমার উপরই আমি বিশ্বাস করি এবং তোমার রিযিকেই আমি আমার রোজা ভঙ্গ করি। তোমার রহমতে, হে করুণাময়দের মধ্যে পরম করুণাময়।\"</p>\n\n                    <h5>সুন্নত দুআঃ</h5>\n                    <div class=\"tutorial-arabic\">ذَهَبَ الظَّمَأُ وَابْتَلَّتِ الْعُرُوقُ وَثَبَتَ الْأَجْرُ إِنْ شَاءَ اللَّهُ</div>\n                    <div class=\"tutorial-pronunciation\">🔊 Dhahaba adh-dhama'u wabtallatil-'uruqu wa thabatal-ajru in sha Allah</div>\n                    <p>\"তৃষ্ণা মিটে গেছে, শিরাগুলো সিক্ত হয়ে গেছে, আর পুরস্কার নিশ্চিত, যদি আল্লাহ চান।\" (সুনানে আবি দাউদ 2357)</p>\n\n                    <h4>সুহুর (প্রাক-ভোর খাবার)</h4>\n                    <p>নবী সাল্লাল্লাহু আলাইহি ওয়াসাল্লাম বলেছেনঃ <em>\"সেহরী খাও, কেননা সেহরীতে বরকত রয়েছে।\"</em> (সহীহ বুখারী 1923 ও সহীহ মুসলিম 1095)</p>\n\n                    <h4>কারা অব্যাহতিপ্রাপ্ত?</h4>\n                    <p>(কুরআন 2:184-185 এর উপর ভিত্তি করে)</p>\n                    <ul>\n                        <li>অসুস্থ বা ওষুধে</li>\n                        <li>ভ্রমণকারী</li>\n                        <li>গর্ভবতী, বুকের দুধ খাওয়ানো বা ঋতুস্রাব করা মহিলারা</li>\n                        <li>বৃদ্ধ যারা রোজা রাখতে পারে না</li>\n                        <li>বয়ঃসন্ধির আগে শিশু</li>\n                    </ul>\n                ",
      "ar": "\n                    <h4>ما هو الصوم؟</h4>\n                    <p>الصيام من الفجر (الفجر) إلى غروب الشمس (المغرب)، والامتناع عن الطعام والشراب والتدخين والعلاقات الزوجية. (القرآن 2:183)</p>\n                    \n                    <h4>النية (النية) لبدء الصيام</h4>\n                    <div class=\"tutorial-arabic\">نَوَيْتُ أَنْ أَصُومَ غَدًا مِنْ شَهْرِ رَمَضَانَ الْمُبَارَكِ فَرْضًا لِلَّهِ تَعَالَى</div>\n                    <div class=\"tutorial-pronunciation\">🔊 Nawaytu an asuma ghadan min shahri ramadanal mubarak fardhan lillahi ta'ala</div>\n                    <p>\"أنوي أن أصوم غداً شهر رمضان المبارك فريضةً على الله تعالى\".</p>\n\n                    <h4>دعاء الإفطار (الإفطار)</h4>\n                    <h5>الدعاء المشترك/الممتد:</h5>\n                    <div class=\"tutorial-arabic\">اللَّهُمَّ إِنِّي لَكَ صُمْتُ وَبِكَ آمَنْتُ وَعَلَى رِزْقِكَ أَفْطَرْتُ بِرَحْمَتِكَ يَا أَرْحَمَ الرَّاحِمِينَ</div>\n                    <div class=\"tutorial-pronunciation\">🔊 Allahumma inni laka sumtu, wa bika aamantu, wa 'ala rizqika aftartu, birahmatika ya Arhamar Raahimeen</div>\n                    <p>\"اللهم لك صمت، وبك آمنت، وعلى رزقك أفطرت، برحمتك يا أرحم الراحمين\".</p>\n\n                    <h5>دعاء السنة:</h5>\n                    <div class=\"tutorial-arabic\">ذَهَبَ الظَّمَأُ وَابْتَلَّتِ الْعُرُوقُ وَثَبَتَ الْأَجْرُ إِنْ شَاءَ اللَّهُ</div>\n                    <div class=\"tutorial-pronunciation\">🔊 Dhahaba adh-dhama'u wabtallatil-'uruqu wa thabatal-ajru in sha Allah</div>\n                    <p>\"ذهب الظمأ، وابتلت العروق، وثبت الأجر إن شاء الله\". (سنن أبي داود 2357)</p>\n\n                    <h4>السحور (وجبة ما قبل الفجر)</h4>\n                    <p>قال النبي ﷺ : <em>«تسحروا فإن في السحور بركة».</em> (صحيح البخاري 1923 وصحيح مسلم 1095)</p>\n\n                    <h4>من هو المعفى؟</h4>\n                    <p>(بناء على القرآن 2: 184-185)</p>\n                    <ul>\n                        <li>المرضى أو الذين يتناولون الدواء</li>\n                        <li>المسافرون</li>\n                        <li>النساء الحوامل أو المرضعات أو الحائض</li>\n                        <li>كبار السن الذين لا يستطيعون الصيام</li>\n                        <li>الأطفال قبل البلوغ</li>\n                    </ul>\n                "
    }
  },
  {
    "id": 15,
    "title": {
      "en": "Guide to Hajj (Pilgrimage)",
      "bn": "হজের নির্দেশিকা (তীর্থযাত্রা)",
      "ar": "دليل الحج (الحج)"
    },
    "body": {
      "en": "\n                    <p>Hajj is the fifth pillar of Islam, obligatory once in a lifetime for those physically and financially able. <em>\"And [due] to Allah from the people is a pilgrimage to the House - for whoever is able to find thereto a way.\"</em> (Quran 3:97)</p>\n                    <h4>Step-by-Step Guide (Days of Hajj)</h4>\n                    <ol>\n                        <li><strong>Preparation & Ihram (Before 8th Dhul Hijjah):</strong> Pilgrims enter a state of spiritual purity (Ihram) at the Miqat, wearing two white unstitched sheets (men) or modest clothing (women). The Talbiyah is chanted constantly.</li>\n                        <li><strong>Day 1: 8th Dhul Hijjah (Mina):</strong> Pilgrims travel to the tent city of Mina, spending the day and night in prayer, reflection, and preparation for Arafat.</li>\n                        <li><strong>Day 2: 9th Dhul Hijjah (Arafat & Muzdalifah):</strong> The climax of Hajj. Pilgrims stand on the plains of Arafat from noon till sunset, begging Allah for forgiveness (Wuquf). The Prophet ﷺ said, <em>\"Hajj is Arafat\"</em> (Tirmidhi 889). After sunset, they travel to Muzdalifah to spend the night under the stars and collect pebbles for the stoning ritual.</li>\n                        <li><strong>Day 3: 10th Dhul Hijjah (Eid al-Adha & Yawm an-Nahr):</strong> A busy day of rituals:\n                            <ul>\n                                <li><strong>Rami:</strong> Stoning the largest Jamarah (pillar) representing the devil with 7 pebbles.</li>\n                                <li><strong>Qurbani:</strong> Animal sacrifice.</li>\n                                <li><strong>Halq/Taqsir:</strong> Shaving the head (men) or trimming the hair (women) to officially leave the restricted state of Ihram.</li>\n                                <li><strong>Tawaf al-Ifadah:</strong> Returning to Mecca to circle the Ka'bah 7 times, followed by Sa'i (walking 7 times between Safa and Marwah).</li>\n                            </ul>\n                        </li>\n                        <li><strong>Days 4-6: 11th-13th Dhul Hijjah (Ayyam al-Tashreeq):</strong> Pilgrims return to Mina. On each of these days, they stone all three Jamarat (small, medium, large) with 7 pebbles each.</li>\n                        <li><strong>Farewell Tawaf (Tawaf al-Wida):</strong> Before leaving Mecca, pilgrims perform one final Tawaf around the Ka'bah, marking the end of their journey.</li>\n                    </ol>\n                    <h4>Talbiyah</h4>\n                    <div class=\"tutorial-arabic\">لَبَّيْكَ اللَّهُمَّ لَبَّيْكَ، لَبَّيْكَ لَا شَرِيكَ لَكَ لَبَّيْكَ، إِنَّ الْحَمْدَ وَالنِّعْمَةَ لَكَ وَالْمُلْكَ، لَا شَرِيكَ لَكَ</div>\n                    <div class=\"tutorial-pronunciation\">🔊 Labbayk Allahumma labbayk. Labbayk la sharika laka labbayk. Innal-hamda wan-ni'mata laka wal-mulk. La sharika lak.</div>\n                    <p>\"Here I am, O Allah, here I am. You have no partner. All praise, grace, and sovereignty are Yours.\" (Sahih Bukhari 1549)</p>\n                    <h4>Best Dua at Arafat</h4>\n                    <div class=\"tutorial-arabic\">لَا إِلَهَ إِلَّا اللَّهُ وَحْدَهُ لَا شَرِيكَ لَهُ، لَهُ الْمُلْكُ وَلَهُ الْحَمْدُ وَهُوَ عَلَى كُلِّ شَيْءٍ قَدِيرٌ</div>\n                    <div class=\"tutorial-pronunciation\">🔊 La ilaha illallahu wahdahu la sharika lah, lahul-mulku wa lahul-hamdu wa huwa 'ala kulli shay'in qadeer</div>\n                    <p>(Tirmidhi 3585)</p>\n                ",
      "bn": "\n                    <p>হজ হল ইসলামের পঞ্চম স্তম্ভ, যারা শারীরিক ও আর্থিকভাবে সক্ষম তাদের জন্য জীবনে একবার ফরজ। <em>\"এবং আল্লাহর জন্য মানুষের পক্ষ থেকে গৃহের হজ্ব- যে ব্যক্তি সেখানে যাওয়ার পথ খুঁজে পেতে পারে।\"</em> (কুরআন 3:97)</p>\n                    <h4>ধাপে ধাপে নির্দেশিকা (হজের দিন)</h4>\n                    <ol>\n                        <li><strong>প্রস্তুতি ও ইহরাম (৮ই যিলহজ্জের আগে):</strong> তীর্থযাত্রীরা মীকাতে আধ্যাত্মিক বিশুদ্ধতার (ইহরাম) অবস্থায় প্রবেশ করে, দুটি সাদা সেলাইবিহীন চাদর (পুরুষ) বা শালীন পোশাক (মহিলা) পরে। প্রতিনিয়ত তালবিয়া উচ্চারণ করা হয়।</li>\n                        <li><strong>দিন 1: 8 ই যিলহজ্জ (মিনা):</strong> তীর্থযাত্রীরা মিনায় তাঁবুর শহর ভ্রমণ করে, দিনরাত প্রার্থনা, প্রতিফলন এবং আরাফাতের প্রস্তুতিতে ব্যয় করে।</li>\n                        <li><strong>২য় দিন: ৯ই জুল হিজ্জাহ (আরাফাত ও মুজদালিফা):</strong> হজের ক্লাইম্যাক্স। তীর্থযাত্রীরা দুপুর থেকে সূর্যাস্ত পর্যন্ত আরাফাতের ময়দানে দাঁড়িয়ে আল্লাহর কাছে ক্ষমা প্রার্থনা করে (উকুফ)। রাসূলুল্লাহ সাল্লাল্লাহু আলাইহি ওয়াসাল্লাম বলেছেন, <em>\"হজ হল আরাফাত\"</em> (তিরমিযী ৮৮৯)। সূর্যাস্তের পর তারা তারার নিচে রাত কাটাতে এবং পাথর মারার অনুষ্ঠানের জন্য নুড়ি সংগ্রহ করতে মুজদালিফায় যাত্রা করে।</li>\n                        <li><strong>দিন 3: 10 তম জুল হিজ্জা (ঈদ আল-আযহা এবং ইয়াওম আন-নাহর):</strong> আচার-অনুষ্ঠানের ব্যস্ত দিন:\n                            <ul>\n                                <li><strong>রামি:</strong> 7টি নুড়ি দিয়ে শয়তানের প্রতিনিধিত্বকারী বৃহত্তম জামারাহ (স্তম্ভ) পাথর ছুড়ে মারা।</li>\n                                <li><strong>কুরবানীঃ</strong> পশু বলি।</li>\n                                <li><strong>হালক/তাকসির:</strong> মাথা ন্যাড়া করা (পুরুষ) বা চুল ছাঁটা (মহিলা) আনুষ্ঠানিকভাবে ইহরামের সীমাবদ্ধ অবস্থা ত্যাগ করার জন্য।</li>\n                                <li><strong>তাওয়াফ আল-ইফাদাহ:</strong> কাবাকে ৭ বার প্রদক্ষিণ করতে মক্কায় প্রত্যাবর্তন, এরপর সাঈ (সাফা ও মারওয়ার মধ্যে ৭ বার হাঁটা)।</li>\n                            </ul>\n                        </li>\n                        <li><strong>দিন 4-6: 11-13 জুল হিজ্জাহ (আইয়াম আল-তাশরীক):</strong> হজযাত্রীরা মিনায় ফিরছেন। এই দিনে, তারা তিনটি জামরাত (ছোট, মাঝারি, বড়) প্রতিটিতে 7টি নুড়ি দিয়ে পাথর মেরেছে।</li>\n                        <li><strong>বিদায়ী তাওয়াফ (তাওয়াফ আল-উইদা):</strong> মক্কা ত্যাগ করার আগে, তীর্থযাত্রীরা তাদের যাত্রার সমাপ্তি চিহ্নিত করে কাবার চারপাশে একটি চূড়ান্ত তাওয়াফ করেন।</li>\n                    </ol>\n                    <h4>তালবিয়াহ</h4>\n                    <div class=\"tutorial-arabic\">لَبَّيْكَ اللَّهُمَّ لَبَّيْكَ، لَبَّيْكَ لَا شَرِيكَ لَكَ لَبَّيْكَ، إِنَّ الْحَمْدَ وَالنِّعْمَةَ لَكَ وَالْمُلْكَ، لَا شَرِيكَ لَكَ</div>\n                    <div class=\"tutorial-pronunciation\">🔊 Labbayk Allahumma labbayk. Labbayk la sharika laka labbayk. Innal-hamda wan-ni'mata laka wal-mulk. La sharika lak.</div>\n                    <p>\"আমি এখানে, হে আল্লাহ, আমি এখানে আছি। তোমার কোন শরীক নেই। সমস্ত প্রশংসা, অনুগ্রহ এবং সার্বভৌমত্ব তোমার।\" (সহীহ বুখারী 1549)</p>\n                    <h4>আরাফাতে শ্রেষ্ঠ দুআ</h4>\n                    <div class=\"tutorial-arabic\">لَا إِلَهَ إِلَّا اللَّهُ وَحْدَهُ لَا شَرِيكَ لَهُ، لَهُ الْمُلْكُ وَلَهُ الْحَمْدُ وَهُوَ عَلَى كُلِّ شَيْءٍ قَدِيرٌ</div>\n                    <div class=\"tutorial-pronunciation\">🔊 La ilaha illallahu wahdahu la sharika lah, lahul-mulku wa lahul-hamdu wa huwa 'ala kulli shay'in qadeer</div>\n                    <p>(তিরমিযী ৩৫৮৫)</p>\n                ",
      "ar": "\n                    <p>الحج هو الركن الخامس من أركان الإسلام، وهو واجب مرة واحدة في العمر على القادرين بدنياً ومالياً. <em>\"ولله على الناس حج البيت من استطاع إليه سبيلا\".</em> (القرآن 3:97)</p>\n                    <h4>دليل خطوة بخطوة (أيام الحج)</h4>\n                    <ol>\n                        <li><strong>الاستعداد والإحرام (قبل الثامن من ذي الحجة):</strong> يدخل الحجاج في حالة طهارة روحية (الإحرام) في الميقات، وهم يرتدون ملاءتين أبيضتين غير مخيطتين (للرجال) أو ملابس محتشمة (للنساء). يتم ترديد التلبية باستمرار.</li>\n                        <li><strong>اليوم الأول: الثامن من ذي الحجة (منى):</strong> يسافر الحجاج إلى مدينة الخيام في منى، حيث يقضون النهار والليل في الصلاة والتأمل والاستعداد لعرفات.</li>\n                        <li><strong>اليوم الثاني: التاسع من ذي الحجة (عرفات ومزدلفة):</strong> ذروة الحج. يقف الحجاج في صعيد عرفات من الظهر حتى غروب الشمس مستغفرين الله (الوقوف). قال النبي صلي الله عليه وسلم <em>\"الحج عرفة\"</em> (الترمذي 889). وبعد غروب الشمس، يسافرون إلى مزدلفة لقضاء الليل تحت النجوم وجمع الحصى لرمي الجمرات.</li>\n                        <li><strong>اليوم الثالث: العاشر من ذي الحجة (عيد الأضحى ويوم النهر):</strong> يوم حافل بالطقوس:\n                            <ul>\n                                <li><strong>رامي:</strong> رمي الجمرة الكبرى التي تمثل الشيطان بسبع حصيات.</li>\n                                <li><strong>قرباني:</strong> التضحية بالحيوان.</li>\n                                <li><strong>الحلق/تقصير:</strong> حلق الرأس (للرجال) أو قص الشعر (للنساء) للخروج رسمياً من حالة الإحرام المقيدة.</li>\n                                <li><strong>طواف الإفاضة:</strong> العودة إلى مكة للطواف حول الكعبة 7 مرات، يليها السعي (المشي 7 مرات بين الصفا والمروة).</li>\n                            </ul>\n                        </li>\n                        <li><strong>الأيام 4-6: 11-13 ذي الحجة (أيام التشريق):</strong> عودة الحجاج إلى منى. ويرميون في كل يوم من هذه الأيام الجمرات الثلاث (الصغيرة والمتوسطة والكبيرة) بسبع حصيات.</li>\n                        <li><strong>طواف الوداع (طواف الوداع):</strong> قبل مغادرة مكة، يؤدي الحجاج طوافًا أخيرًا حول الكعبة، إيذانًا بنهاية رحلتهم.</li>\n                    </ol>\n                    <h4>تلبيية</h4>\n                    <div class=\"tutorial-arabic\">لَبَّيْكَ اللَّهُمَّ لَبَّيْكَ، لَبَّيْكَ لَا شَرِيكَ لَكَ لَبَّيْكَ، إِنَّ الْحَمْدَ وَالنِّعْمَةَ لَكَ وَالْمُلْكَ، لَا شَرِيكَ لَكَ</div>\n                    <div class=\"tutorial-pronunciation\">🔊 Labbayk Allahumma labbayk. Labbayk la sharika laka labbayk. Innal-hamda wan-ni'mata laka wal-mulk. La sharika lak.</div>\n                    <p>\" لبيك اللهم لبيك لا شريك لك، لك الحمد والنعمة والملك \". (صحيح البخاري ١٥٤٩)</p>\n                    <h4>أفضل الدعاء على عرفات</h4>\n                    <div class=\"tutorial-arabic\">لَا إِلَهَ إِلَّا اللَّهُ وَحْدَهُ لَا شَرِيكَ لَهُ، لَهُ الْمُلْكُ وَلَهُ الْحَمْدُ وَهُوَ عَلَى كُلِّ شَيْءٍ قَدِيرٌ</div>\n                    <div class=\"tutorial-pronunciation\">🔊 La ilaha illallahu wahdahu la sharika lah, lahul-mulku wa lahul-hamdu wa huwa 'ala kulli shay'in qadeer</div>\n                    <p>(الترمذي 3585)</p>\n                "
    }
  }
]